amplitude_tracker/__init__.py
amplitude_tracker/client.py
amplitude_tracker/consumer.py
amplitude_tracker/request.py
amplitude_tracker/utils.py
amplitude_tracker/version.py
amplitude_tracker/test/__init__.py
amplitude_tracker/test/client.py
amplitude_tracker/test/consumer.py
amplitude_tracker/test/module.py
amplitude_tracker/test/request.py
amplitude_tracker/test/utils.py
amplitude_tracker-0.0.7.dist-info/METADATA
amplitude_tracker-0.0.7.dist-info/WHEEL
amplitude_tracker-0.0.7.dist-info/top_level.txt
amplitude_tracker-0.0.7.dist-info/RECORD
