Metadata-Version: 2.1
Name: amplitude-tracker
Version: 0.0.7
Summary: The hassle-free way to integrate amplitude into any python application.
Home-page: https://github.com/RandomCoffee/amplitude-python
Author: RandomCoffee
Author-email: tech@random-coffee.com
Maintainer: RandomCoffee
Maintainer-email: tech@random-coffee.com
License: MIT License
Platform: UNKNOWN
Classifier: Development Status :: 5 - Production/Stable
Classifier: Intended Audience :: Developers
Classifier: License :: OSI Approved :: MIT License
Classifier: Operating System :: OS Independent
Classifier: Programming Language :: Python
Classifier: Programming Language :: Python :: 2
Classifier: Programming Language :: Python :: 2.7
Classifier: Programming Language :: Python :: 3
Classifier: Programming Language :: Python :: 3.2
Classifier: Programming Language :: Python :: 3.3
Classifier: Programming Language :: Python :: 3.4
Classifier: Programming Language :: Python :: 3.5
Classifier: Programming Language :: Python :: 3.6
Classifier: Programming Language :: Python :: 3.7
Classifier: Programming Language :: Python :: 3.8
Provides-Extra: test
